{
  "2024-03-09": {
    "count": 3457,
    "timestamp": "2024-03-09T00:00:00Z",
    "uniques": 316
  },
  "2024-03-10": {
    "count": 49660,
    "timestamp": "2024-03-10T00:00:00Z",
    "uniques": 2490
  },
  "2024-03-11": {
    "count": 72861,
    "timestamp": "2024-03-11T00:00:00Z",
    "uniques": 9352
  },
  "2024-03-12": {
    "count": 120970,
    "timestamp": "2024-03-12T00:00:00Z",
    "uniques": 14077
  },
  "2024-03-13": {
    "count": 121470,
    "timestamp": "2024-03-13T00:00:00Z",
    "uniques": 13002
  },
  "2024-03-14": {
    "count": 43487,
    "timestamp": "2024-03-14T00:00:00Z",
    "uniques": 6399
  },
  "2024-03-15": {
    "count": 33484,
    "timestamp": "2024-03-15T00:00:00Z",
    "uniques": 5403
  },
  "2024-03-16": {
    "count": 8197,
    "timestamp": "2024-03-16T00:00:00Z",
    "uniques": 924
  },
  "2024-03-17": {
    "count": 10358,
    "timestamp": "2024-03-17T00:00:00Z",
    "uniques": 1280
  },
  "2024-03-18": {
    "count": 45340,
    "timestamp": "2024-03-18T00:00:00Z",
    "uniques": 7068
  },
  "2024-03-19": {
    "count": 42074,
    "timestamp": "2024-03-19T00:00:00Z",
    "uniques": 6882
  },
  "2024-03-20": {
    "count": 42970,
    "timestamp": "2024-03-20T00:00:00Z",
    "uniques": 6724
  },
  "2024-03-21": {
    "count": 45218,
    "timestamp": "2024-03-21T00:00:00Z",
    "uniques": 6926
  },
  "2024-03-22": {
    "count": 38182,
    "timestamp": "2024-03-22T00:00:00Z",
    "uniques": 5944
  },
  "2024-03-23": {
    "count": 12315,
    "timestamp": "2024-03-23T00:00:00Z",
    "uniques": 1093
  },
  "2024-03-24": {
    "count": 14442,
    "timestamp": "2024-03-24T00:00:00Z",
    "uniques": 1329
  },
  "2024-03-25": {
    "count": 115405,
    "timestamp": "2024-03-25T00:00:00Z",
    "uniques": 12201
  },
  "2024-03-26": {
    "count": 130968,
    "timestamp": "2024-03-26T00:00:00Z",
    "uniques": 12861
  },
  "2024-03-27": {
    "count": 127525,
    "timestamp": "2024-03-27T00:00:00Z",
    "uniques": 13191
  },
  "2024-03-28": {
    "count": 115328,
    "timestamp": "2024-03-28T00:00:00Z",
    "uniques": 12093
  },
  "2024-03-29": {
    "count": 77446,
    "timestamp": "2024-03-29T00:00:00Z",
    "uniques": 6960
  },
  "2024-03-30": {
    "count": 33134,
    "timestamp": "2024-03-30T00:00:00Z",
    "uniques": 2394
  },
  "2024-03-31": {
    "count": 33769,
    "timestamp": "2024-03-31T00:00:00Z",
    "uniques": 2319
  },
  "2024-04-01": {
    "count": 80633,
    "timestamp": "2024-04-01T00:00:00Z",
    "uniques": 8256
  },
  "2024-04-02": {
    "count": 117319,
    "timestamp": "2024-04-02T00:00:00Z",
    "uniques": 12347
  },
  "2024-04-03": {
    "count": 122957,
    "timestamp": "2024-04-03T00:00:00Z",
    "uniques": 12303
  },
  "2024-04-04": {
    "count": 127206,
    "timestamp": "2024-04-04T00:00:00Z",
    "uniques": 11999
  },
  "2024-04-05": {
    "count": 110557,
    "timestamp": "2024-04-05T00:00:00Z",
    "uniques": 10818
  },
  "2024-04-06": {
    "count": 37121,
    "timestamp": "2024-04-06T00:00:00Z",
    "uniques": 2487
  },
  "2024-04-07": {
    "count": 36185,
    "timestamp": "2024-04-07T00:00:00Z",
    "uniques": 2730
  },
  "2024-04-08": {
    "count": 4347,
    "timestamp": "2024-04-08T00:00:00Z",
    "uniques": 811
  }
}
