[
  {
    "downloads": 3234636,
    "major_version": "1",
    "created_at": "2020-06-04"
  },
  {
    "downloads": 12012318,
    "major_version": "2",
    "created_at": "2021-04-26"
  },
  {
    "downloads": 9832931,
    "major_version": "3",
    "created_at": "2022-03-28"
  },
  {
    "downloads": 13351751,
    "major_version": "4",
    "created_at": "2022-08-18"
  },
  {
    "downloads": 4279297,
    "major_version": "5",
    "created_at": "2023-06-05"
  },
  {
    "downloads": 14390963,
    "major_version": "6",
    "created_at": "2023-08-09"
  },
  {
    "downloads": 21747630,
    "major_version": "7",
    "created_at": "2024-01-22"
  }
]