[
  {
    "downloads": 3563764,
    "major_version": "1",
    "created_at": "2020-06-04"
  },
  {
    "downloads": 14054295,
    "major_version": "2",
    "created_at": "2021-04-26"
  },
  {
    "downloads": 12486111,
    "major_version": "3",
    "created_at": "2022-03-28"
  },
  {
    "downloads": 15886585,
    "major_version": "4",
    "created_at": "2022-08-18"
  },
  {
    "downloads": 5201655,
    "major_version": "5",
    "created_at": "2023-06-05"
  },
  {
    "downloads": 19727934,
    "major_version": "6",
    "created_at": "2023-08-09"
  },
  {
    "downloads": 41412583,
    "major_version": "7",
    "created_at": "2024-01-22"
  },
  {
    "downloads": 11446946,
    "major_version": "8",
    "created_at": "2025-06-25"
  }
]