{
  "2024-03-09": {
    "count": 25,
    "timestamp": "2024-03-09T00:00:00Z",
    "uniques": 7
  },
  "2024-03-10": {
    "count": 553,
    "timestamp": "2024-03-10T00:00:00Z",
    "uniques": 83
  },
  "2024-03-11": {
    "count": 981,
    "timestamp": "2024-03-11T00:00:00Z",
    "uniques": 134
  },
  "2024-03-12": {
    "count": 2048,
    "timestamp": "2024-03-12T00:00:00Z",
    "uniques": 281
  },
  "2024-03-13": {
    "count": 1788,
    "timestamp": "2024-03-13T00:00:00Z",
    "uniques": 294
  },
  "2024-03-14": {
    "count": 774,
    "timestamp": "2024-03-14T00:00:00Z",
    "uniques": 113
  },
  "2024-03-15": {
    "count": 383,
    "timestamp": "2024-03-15T00:00:00Z",
    "uniques": 55
  },
  "2024-03-16": {
    "count": 231,
    "timestamp": "2024-03-16T00:00:00Z",
    "uniques": 31
  },
  "2024-03-17": {
    "count": 279,
    "timestamp": "2024-03-17T00:00:00Z",
    "uniques": 24
  },
  "2024-03-18": {
    "count": 345,
    "timestamp": "2024-03-18T00:00:00Z",
    "uniques": 64
  },
  "2024-03-19": {
    "count": 445,
    "timestamp": "2024-03-19T00:00:00Z",
    "uniques": 82
  },
  "2024-03-20": {
    "count": 1799,
    "timestamp": "2024-03-20T00:00:00Z",
    "uniques": 267
  },
  "2024-03-21": {
    "count": 2189,
    "timestamp": "2024-03-21T00:00:00Z",
    "uniques": 320
  },
  "2024-03-22": {
    "count": 1695,
    "timestamp": "2024-03-22T00:00:00Z",
    "uniques": 246
  },
  "2024-03-23": {
    "count": 892,
    "timestamp": "2024-03-23T00:00:00Z",
    "uniques": 104
  },
  "2024-03-24": {
    "count": 674,
    "timestamp": "2024-03-24T00:00:00Z",
    "uniques": 83
  },
  "2024-03-25": {
    "count": 1879,
    "timestamp": "2024-03-25T00:00:00Z",
    "uniques": 254
  },
  "2024-03-26": {
    "count": 2155,
    "timestamp": "2024-03-26T00:00:00Z",
    "uniques": 274
  },
  "2024-03-27": {
    "count": 1929,
    "timestamp": "2024-03-27T00:00:00Z",
    "uniques": 289
  },
  "2024-03-28": {
    "count": 1710,
    "timestamp": "2024-03-28T00:00:00Z",
    "uniques": 231
  },
  "2024-03-29": {
    "count": 1219,
    "timestamp": "2024-03-29T00:00:00Z",
    "uniques": 177
  },
  "2024-03-30": {
    "count": 547,
    "timestamp": "2024-03-30T00:00:00Z",
    "uniques": 84
  },
  "2024-03-31": {
    "count": 525,
    "timestamp": "2024-03-31T00:00:00Z",
    "uniques": 71
  },
  "2024-04-01": {
    "count": 2131,
    "timestamp": "2024-04-01T00:00:00Z",
    "uniques": 259
  },
  "2024-04-02": {
    "count": 1153,
    "timestamp": "2024-04-02T00:00:00Z",
    "uniques": 179
  }
}
