{
  "2024-03-09": {
    "count": 86,
    "timestamp": "2024-03-09T00:00:00Z",
    "uniques": 46
  },
  "2024-03-10": {
    "count": 1767,
    "timestamp": "2024-03-10T00:00:00Z",
    "uniques": 606
  },
  "2024-03-11": {
    "count": 4260,
    "timestamp": "2024-03-11T00:00:00Z",
    "uniques": 1451
  },
  "2024-03-12": {
    "count": 9290,
    "timestamp": "2024-03-12T00:00:00Z",
    "uniques": 2569
  },
  "2024-03-13": {
    "count": 8545,
    "timestamp": "2024-03-13T00:00:00Z",
    "uniques": 2590
  },
  "2024-03-14": {
    "count": 3247,
    "timestamp": "2024-03-14T00:00:00Z",
    "uniques": 1016
  },
  "2024-03-15": {
    "count": 2609,
    "timestamp": "2024-03-15T00:00:00Z",
    "uniques": 935
  },
  "2024-03-16": {
    "count": 360,
    "timestamp": "2024-03-16T00:00:00Z",
    "uniques": 198
  },
  "2024-03-17": {
    "count": 696,
    "timestamp": "2024-03-17T00:00:00Z",
    "uniques": 287
  },
  "2024-03-18": {
    "count": 3116,
    "timestamp": "2024-03-18T00:00:00Z",
    "uniques": 1205
  },
  "2024-03-19": {
    "count": 3259,
    "timestamp": "2024-03-19T00:00:00Z",
    "uniques": 1139
  },
  "2024-03-20": {
    "count": 3331,
    "timestamp": "2024-03-20T00:00:00Z",
    "uniques": 1321
  },
  "2024-03-21": {
    "count": 3237,
    "timestamp": "2024-03-21T00:00:00Z",
    "uniques": 1208
  },
  "2024-03-22": {
    "count": 2759,
    "timestamp": "2024-03-22T00:00:00Z",
    "uniques": 945
  },
  "2024-03-23": {
    "count": 496,
    "timestamp": "2024-03-23T00:00:00Z",
    "uniques": 209
  },
  "2024-03-24": {
    "count": 1733,
    "timestamp": "2024-03-24T00:00:00Z",
    "uniques": 622
  },
  "2024-03-25": {
    "count": 9588,
    "timestamp": "2024-03-25T00:00:00Z",
    "uniques": 2950
  },
  "2024-03-26": {
    "count": 9938,
    "timestamp": "2024-03-26T00:00:00Z",
    "uniques": 2941
  },
  "2024-03-27": {
    "count": 9110,
    "timestamp": "2024-03-27T00:00:00Z",
    "uniques": 2622
  },
  "2024-03-28": {
    "count": 9069,
    "timestamp": "2024-03-28T00:00:00Z",
    "uniques": 2815
  },
  "2024-03-29": {
    "count": 5755,
    "timestamp": "2024-03-29T00:00:00Z",
    "uniques": 1674
  },
  "2024-03-30": {
    "count": 1383,
    "timestamp": "2024-03-30T00:00:00Z",
    "uniques": 494
  },
  "2024-03-31": {
    "count": 1278,
    "timestamp": "2024-03-31T00:00:00Z",
    "uniques": 587
  },
  "2024-04-01": {
    "count": 5042,
    "timestamp": "2024-04-01T00:00:00Z",
    "uniques": 1769
  },
  "2024-04-02": {
    "count": 8860,
    "timestamp": "2024-04-02T00:00:00Z",
    "uniques": 3187
  },
  "2024-04-03": {
    "count": 9355,
    "timestamp": "2024-04-03T00:00:00Z",
    "uniques": 2768
  },
  "2024-04-04": {
    "count": 8396,
    "timestamp": "2024-04-04T00:00:00Z",
    "uniques": 2847
  },
  "2024-04-05": {
    "count": 8165,
    "timestamp": "2024-04-05T00:00:00Z",
    "uniques": 2524
  },
  "2024-04-06": {
    "count": 865,
    "timestamp": "2024-04-06T00:00:00Z",
    "uniques": 508
  }
}
